CONTRIBUTORS.txt
LICENSE
MANIFEST.in
README.md
setup.py
django_searchbar/__init__.py
django_searchbar/admin.py
django_searchbar/forms.py
django_searchbar/mixins.py
django_searchbar/settings.py
django_searchbar/tests.py
django_searchbar/urls.py
django_searchbar/utils.py
django_searchbar/views.py
django_searchbar.egg-info/PKG-INFO
django_searchbar.egg-info/SOURCES.txt
django_searchbar.egg-info/dependency_links.txt
django_searchbar.egg-info/not-zip-safe
django_searchbar.egg-info/top_level.txt