Metadata-Version: 1.1
Name: django-searchbar
Version: 0.1.7
Summary: Simple searchbar and handler you can use in all your views and templates.
Home-page: http://github.com/arsham/django-searchbar
Author: Arsham Shirvani
Author-email: arshamshirvani@gmail.com
License: BSD
Keywords: searchbar,django,forms,template
Platform: OS Independen
Classifier: Programming Language :: Python :: 3
Classifier: Programming Language :: Python :: 3.2
Classifier: Programming Language :: Python :: 3.3
Classifier: Programming Language :: Python :: 3.4
Classifier: Topic :: Software Development :: Libraries
Classifier: Intended Audience :: Developers
Classifier: License :: OSI Approved :: BSD License
Classifier: Operating System :: OS Independent
Classifier: Framework :: Django
Classifier: Environment :: Web Environment
